[
  {
    "id": "BSBeanie.jpg",
    "name": "Beanie",
    "description": "Exclusive B. Sporty Collection",
    "image": "/BSPORTY/BSBeanie.jpg",
    "price": "Contact now to get"
  },
  {
    "id": "BSBlanketBoxW",
    "name": "Blanket Box W",
    "description": "Exclusive B. Sporty Collection",
    "image": "/BSPORTY/BSBlanketBoxW/throw-blanket-50x60-front-6931dd58613a8.jpg",
    "price": "Contact now to get"
  },
  {
    "id": "BSBlanketLogoW",
    "name": "Blanket Logo W",
    "description": "Exclusive B. Sporty Collection",
    "image": "/BSPORTY/BSBlanketLogoW/throw-blanket-50x60-front-6931df78d2f9b.jpg",
    "price": "Contact now to get"
  },
  {
    "id": "BSBlanketSW",
    "name": "Blanket S W",
    "description": "Exclusive B. Sporty Collection",
    "image": "/BSPORTY/BSBlanketSW/throw-blanket-50x60-front-6931ddb382e81.jpg",
    "price": "Contact now to get"
  },
  {
    "id": "BSBlanketW",
    "name": "Blanket W",
    "description": "Exclusive B. Sporty Collection",
    "image": "/BSPORTY/BSBlanketW/throw-blanket-50x60-front-6931dd152c36a.jpg",
    "price": "Contact now to get"
  },
  {
    "id": "BSBlanketZ",
    "name": "Blanket Z",
    "description": "Exclusive B. Sporty Collection",
    "image": "/BSPORTY/BSBlanketZ/throw-blanket-50x60-front-6931cb5d69f41.jpg",
    "price": "Contact now to get"
  },
  {
    "id": "BSDuffleAB",
    "name": "Duffle A B",
    "description": "Exclusive B. Sporty Collection",
    "image": "/BSPORTY/BSDuffleAB/all-over-print-duffle-bag-white-front-6931db0dbfbfd.jpg",
    "price": "Contact now to get"
  },
  {
    "id": "BSDuffleATB",
    "name": "Duffle A T B",
    "description": "Exclusive B. Sporty Collection",
    "image": "/BSPORTY/BSDuffleATB/all-over-print-duffle-bag-white-front-6931dbfd1baf2.jpg",
    "price": "Contact now to get"
  },
  {
    "id": "BSDuffleAW",
    "name": "Duffle A W",
    "description": "Exclusive B. Sporty Collection",
    "image": "/BSPORTY/BSDuffleAW/all-over-print-duffle-bag-white-front-6931db9078cf4.jpg",
    "price": "Contact now to get"
  },
  {
    "id": "BSDuffleB",
    "name": "Duffle B",
    "description": "Exclusive B. Sporty Collection",
    "image": "/BSPORTY/BSDuffleB/all-over-print-duffle-bag-white-front-6931db62de613.jpg",
    "price": "Contact now to get"
  },
  {
    "id": "BSDuffleW",
    "name": "Duffle W",
    "description": "Exclusive B. Sporty Collection",
    "image": "/BSPORTY/BSDuffleW/all-over-print-duffle-bag-white-front-6931dbc5e2e8e.jpg",
    "price": "Contact now to get"
  },
  {
    "id": "BSFannyB",
    "name": "Fanny B",
    "description": "Exclusive B. Sporty Collection",
    "image": "/BSPORTY/BSFannyB/all-over-print-fanny-pack-white-front-6931e52bb839e.jpg",
    "price": "Contact now to get"
  },
  {
    "id": "BSFannyCB",
    "name": "Fanny C B",
    "description": "Exclusive B. Sporty Collection",
    "image": "/BSPORTY/BSFannyCB/all-over-print-fanny-pack-white-front-6931e5654ee05.jpg",
    "price": "Contact now to get"
  },
  {
    "id": "BSFannyLogoB",
    "name": "Fanny Logo B",
    "description": "Exclusive B. Sporty Collection",
    "image": "/BSPORTY/BSFannyLogoB/all-over-print-fanny-pack-white-front-6931e4fa05b62.jpg",
    "price": "Contact now to get"
  },
  {
    "id": "BSFannyLogoW",
    "name": "Fanny Logo W",
    "description": "Exclusive B. Sporty Collection",
    "image": "/BSPORTY/BSFannyLogoW/all-over-print-fanny-pack-white-front-6931e4c697211.jpg",
    "price": "Contact now to get"
  },
  {
    "id": "BSHOODIEB",
    "name": "H O O D I E B",
    "description": "Exclusive B. Sporty Collection",
    "image": "/BSPORTY/BSHOODIEB/unisex-heavy-blend-hoodie-black-front-6952cd1a5f854.jpg",
    "price": "Contact now to get"
  },
  {
    "id": "BSHOODIEW",
    "name": "H O O D I E W",
    "description": "Exclusive B. Sporty Collection",
    "image": "/BSPORTY/BSHOODIEW/unisex-heavy-blend-hoodie-white-front-6952c9970d36a.jpg",
    "price": "Contact now to get"
  },
  {
    "id": "BSHandsoap",
    "name": "Handsoap",
    "description": "Exclusive B. Sporty Collection",
    "image": "/BSPORTY/BSHandsoap/refreshing-hand--body-lotion-white-front-6931dad309b5b.jpg",
    "price": "Contact now to get"
  },
  {
    "id": "BSHatB",
    "name": "Hat B",
    "description": "Exclusive B. Sporty Collection",
    "image": "/BSPORTY/BSHatB/classic-dad-hat-black-front-6931c9111da74.jpg",
    "price": "Contact now to get"
  },
  {
    "id": "BSHatW",
    "name": "Hat W",
    "description": "Exclusive B. Sporty Collection",
    "image": "/BSPORTY/BSHatW/classic-dad-hat-white-front-6931c98e7f671.jpg",
    "price": "Contact now to get"
  },
  {
    "id": "BSHoddieB",
    "name": "Hoddie B",
    "description": "Exclusive B. Sporty Collection",
    "image": "/BSPORTY/BSHoddieB/unisex-eco-raglan-hoodie-black-front-6932533ecd0c8.jpg",
    "price": "Contact now to get"
  },
  {
    "id": "BSLongSleeveB",
    "name": "Long Sleeve B",
    "description": "Exclusive B. Sporty Collection",
    "image": "/BSPORTY/BSLongSleeveB/unisex-garment-dyed-heavyweight-long-sleeve-shirt-black-front-6931c719aa2c6.jpg",
    "price": "Contact now to get"
  },
  {
    "id": "BSLongSleeveBB",
    "name": "Long Sleeve B B",
    "description": "Exclusive B. Sporty Collection",
    "image": "/BSPORTY/BSLongSleeveBB/unisex-garment-dyed-heavyweight-long-sleeve-shirt-black-front-6931c7ce49e79.jpg",
    "price": "Contact now to get"
  },
  {
    "id": "BSLongSleeveWB",
    "name": "Long Sleeve W B",
    "description": "Exclusive B. Sporty Collection",
    "image": "/BSPORTY/BSLongSleeveWB/unisex-garment-dyed-heavyweight-long-sleeve-shirt-white-front-6931c81949a35.jpg",
    "price": "Contact now to get"
  },
  {
    "id": "BSMenSlides",
    "name": "Men Slides",
    "description": "Exclusive B. Sporty Collection",
    "image": "/BSPORTY/BSMenSlides/mens-slides-black-front-2-6931c9ce5eec9.jpg",
    "price": "Contact now to get"
  },
  {
    "id": "BSMugBS",
    "name": "Mug B S",
    "description": "Exclusive B. Sporty Collection",
    "image": "/BSPORTY/BSMugBS/enamel-mug-white-12-oz-front-6931cba939d13.jpg",
    "price": "Contact now to get"
  },
  {
    "id": "BSMugW",
    "name": "Mug W",
    "description": "Exclusive B. Sporty Collection",
    "image": "/BSPORTY/BSMugW/enamel-mug-white-12-oz-front-6931cb866b8fa.jpg",
    "price": "Contact now to get"
  },
  {
    "id": "BSMugWS",
    "name": "Mug W S",
    "description": "Exclusive B. Sporty Collection",
    "image": "/BSPORTY/BSMugWS/enamel-mug-white-12-oz-front-6931cbc72d87b.jpg",
    "price": "Contact now to get"
  },
  {
    "id": "BSPillowB",
    "name": "Pillow B",
    "description": "Exclusive B. Sporty Collection",
    "image": "/BSPORTY/BSPillowB/all-over-print-basic-pillow-18x18-front-6931ccc50feb6.jpg",
    "price": "Contact now to get"
  },
  {
    "id": "BSPillowBB",
    "name": "Pillow B B",
    "description": "Exclusive B. Sporty Collection",
    "image": "/BSPORTY/BSPillowBB/all-over-print-premium-pillow-18x18-front-6931da7242f9c.jpg",
    "price": "Contact now to get"
  },
  {
    "id": "BSPillowW",
    "name": "Pillow W",
    "description": "Exclusive B. Sporty Collection",
    "image": "/BSPORTY/BSPillowW/all-over-print-basic-pillow-18x18-front-6931dc428fc52.jpg",
    "price": "Contact now to get"
  },
  {
    "id": "BSPoster",
    "name": "Poster",
    "description": "Exclusive B. Sporty Collection",
    "image": "/BSPORTY/BSPoster/matte-paper-framed-poster-with-mat-(in)-black-12x16-front-6931ddf2bc22e.jpg",
    "price": "Contact now to get"
  },
  {
    "id": "BSSocksB",
    "name": "Socks B",
    "description": "Exclusive B. Sporty Collection",
    "image": "/BSPORTY/BSSocksB/embroidered-crew-socks-black-left-6931ca46cc7aa.jpg",
    "price": "Contact now to get"
  },
  {
    "id": "BSSocksW",
    "name": "Socks W",
    "description": "Exclusive B. Sporty Collection",
    "image": "/BSPORTY/BSSocksW/embroidered-crew-socks-white-left-6931ca6361ff0.jpg",
    "price": "Contact now to get"
  },
  {
    "id": "BSSportsBraW",
    "name": "Sports Bra W",
    "description": "Exclusive B. Sporty Collection",
    "image": "/BSPORTY/BSSportsBraW/all-over-print-padded-sports-bra-white-front-6931cc0c63816.jpg",
    "price": "Contact now to get"
  },
  {
    "id": "BSSportsBraZBPipping",
    "name": "Sports Bra Z B Pipping",
    "description": "Exclusive B. Sporty Collection",
    "image": "/BSPORTY/BSSportsBraZBPipping/all-over-print-padded-sports-bra-black-front-6931cc8b798b3.jpg",
    "price": "Contact now to get"
  },
  {
    "id": "BSSportsBraZWPipping",
    "name": "Sports Bra Z W Pipping",
    "description": "Exclusive B. Sporty Collection",
    "image": "/BSPORTY/BSSportsBraZWPipping/all-over-print-padded-sports-bra-white-front-6931cc5668900.jpg",
    "price": "Contact now to get"
  },
  {
    "id": "BSSweatpantsB",
    "name": "Sweatpants B",
    "description": "Exclusive B. Sporty Collection",
    "image": "/BSPORTY/BSSweatpantsB/unisex-fleece-sweatpants-black-front-6931c86884b88.jpg",
    "price": "Contact now to get"
  },
  {
    "id": "BSSweatpantsW",
    "name": "Sweatpants W",
    "description": "Exclusive B. Sporty Collection",
    "image": "/BSPORTY/BSSweatpantsW/unisex-fleece-sweatpants-white-front-6931c8a989c91.jpg",
    "price": "Contact now to get"
  },
  {
    "id": "BSToteB",
    "name": "Tote B",
    "description": "Exclusive B. Sporty Collection",
    "image": "/BSPORTY/BSToteB/all-over-print-large-tote-bag-w-pocket-black-front-6931cac8c000a.jpg",
    "price": "Contact now to get"
  },
  {
    "id": "BSToteZ",
    "name": "Tote Z",
    "description": "Exclusive B. Sporty Collection",
    "image": "/BSPORTY/BSToteZ/all-over-print-large-tote-bag-w-pocket-black-front-6931cb1573644.jpg",
    "price": "Contact now to get"
  },
  {
    "id": "BSTumblerLogoB",
    "name": "Tumbler Logo B",
    "description": "Exclusive B. Sporty Collection",
    "image": "/BSPORTY/BSTumblerLogoB/stainless-steel-tumbler-black-front-6931dea66be41.jpg",
    "price": "Contact now to get"
  },
  {
    "id": "BSTumblerLogoW",
    "name": "Tumbler Logo W",
    "description": "Exclusive B. Sporty Collection",
    "image": "/BSPORTY/BSTumblerLogoW/stainless-steel-tumbler-white-front-6931df342177a.jpg",
    "price": "Contact now to get"
  },
  {
    "id": "BSWaterBottleW",
    "name": "Water Bottle W",
    "description": "Exclusive B. Sporty Collection",
    "image": "/BSPORTY/BSWaterBottleW/stainless-steel-water-bottle-with-a-straw-lid-white-32-oz-front-6931de2e6d9a2.jpg",
    "price": "Contact now to get"
  },
  {
    "id": "BSWaterBottleWLogo",
    "name": "Water Bottle W Logo",
    "description": "Exclusive B. Sporty Collection",
    "image": "/BSPORTY/BSWaterBottleWLogo/stainless-steel-water-bottle-with-a-straw-lid-white-32-oz-front-6931de6326b66.jpg",
    "price": "Contact now to get"
  },
  {
    "id": "BSWideSweatpantsBackB",
    "name": "Wide Sweatpants Back B",
    "description": "Exclusive B. Sporty Collection",
    "image": "/BSPORTY/BSWideSweatpantsBackB/all-over-print-unisex-wide-leg-pants-white-front-695d3e75373ca.jpg",
    "price": "Contact now to get"
  },
  {
    "id": "BSWideSweatpantsBackW",
    "name": "Wide Sweatpants Back W",
    "description": "Exclusive B. Sporty Collection",
    "image": "/BSPORTY/BSWideSweatpantsBackW/all-over-print-unisex-wide-leg-pants-white-front-695d3eb6a8c94.jpg",
    "price": "Contact now to get"
  },
  {
    "id": "BSWideSweatpantsFrontB",
    "name": "Wide Sweatpants Front B",
    "description": "Exclusive B. Sporty Collection",
    "image": "/BSPORTY/BSWideSweatpantsFrontB/all-over-print-unisex-wide-leg-pants-white-front-695d3da4c96ee.jpg",
    "price": "Contact now to get"
  },
  {
    "id": "BSWideSweatpantsFrontW",
    "name": "Wide Sweatpants Front W",
    "description": "Exclusive B. Sporty Collection",
    "image": "/BSPORTY/BSWideSweatpantsFrontW/all-over-print-unisex-wide-leg-pants-white-front-695d3d1b7d0fe.jpg",
    "price": "Contact now to get"
  },
  {
    "id": "BSWomenSlides",
    "name": "Women Slides",
    "description": "Exclusive B. Sporty Collection",
    "image": "/BSPORTY/BSWomenSlides/womens-slides-white-front-2-6931c9fb90653.jpg",
    "price": "Contact now to get"
  },
  {
    "id": "BSZipHoddieB",
    "name": "Zip Hoddie B",
    "description": "Exclusive B. Sporty Collection",
    "image": "/BSPORTY/BSZipHoddieB/unisex-heavy-blend-zip-hoodie-black-front-6932509c2f92f.jpg",
    "price": "Contact now to get"
  },
  {
    "id": "BSZipHoddieEB",
    "name": "Zip Hoddie E B",
    "description": "Exclusive B. Sporty Collection",
    "image": "/BSPORTY/BSZipHoddieEB/unisex-heavy-blend-zip-hoodie-black-front-693251567724d.jpg",
    "price": "Contact now to get"
  },
  {
    "id": "BSZipHoddieLeftW",
    "name": "Zip Hoddie Left W",
    "description": "Exclusive B. Sporty Collection",
    "image": "/BSPORTY/BSZipHoddieLeftW/unisex-heavy-blend-zip-hoodie-white-front-693250e938979.jpg",
    "price": "Contact now to get"
  },
  {
    "id": "BSZipHoddieW",
    "name": "Zip Hoddie W",
    "description": "Exclusive B. Sporty Collection",
    "image": "/BSPORTY/BSZipHoddieW/unisex-heavy-blend-zip-hoodie-white-front-693252cceaaed.jpg",
    "price": "Contact now to get"
  }
]
